pytiled_parser/__init__.py
pytiled_parser/common_types.py
pytiled_parser/exception.py
pytiled_parser/layer.py
pytiled_parser/parser.py
pytiled_parser/properties.py
pytiled_parser/py.typed
pytiled_parser/tiled_map.py
pytiled_parser/tiled_object.py
pytiled_parser/tileset.py
pytiled_parser/util.py
pytiled_parser/wang_set.py
pytiled_parser/world.py
pytiled_parser/parsers/__init__.py
pytiled_parser/parsers/json/__init__.py
pytiled_parser/parsers/json/layer.py
pytiled_parser/parsers/json/properties.py
pytiled_parser/parsers/json/tiled_map.py
pytiled_parser/parsers/json/tiled_object.py
pytiled_parser/parsers/json/tileset.py
pytiled_parser/parsers/json/wang_set.py
pytiled_parser/parsers/tmx/__init__.py
pytiled_parser/parsers/tmx/layer.py
pytiled_parser/parsers/tmx/properties.py
pytiled_parser/parsers/tmx/tiled_map.py
pytiled_parser/parsers/tmx/tiled_object.py
pytiled_parser/parsers/tmx/tileset.py
pytiled_parser/parsers/tmx/wang_set.py
pytiled_parser-2.2.8.dist-info/LICENSE
pytiled_parser-2.2.8.dist-info/METADATA
pytiled_parser-2.2.8.dist-info/WHEEL
pytiled_parser-2.2.8.dist-info/top_level.txt
pytiled_parser-2.2.8.dist-info/RECORD
