Metadata-Version: 2.2
Name: pytiled_parser
Version: 2.2.8
Summary: A library for parsing Tiled Map Editor maps and tilesets
Author-email: Benjamin Kirkbride <BenjaminKirkbride@gmail.com>, Darren Eberly <Darren.Eberly@gmail.com>
Maintainer-email: Darren Eberly <Darren.Eberly@gmail.com>
License: MIT License
Project-URL: homepage, https://github.com/pythonarcade/pytiled_parser
Classifier: Development Status :: 5 - Production/Stable
Classifier: Intended Audience :: Developers
Classifier: License :: OSI Approved :: MIT License
Classifier: Operating System :: OS Independent
Classifier: Programming Language :: Python
Classifier: Programming Language :: Python :: 3.6
Classifier: Programming Language :: Python :: 3.7
Classifier: Programming Language :: Python :: 3.8
Classifier: Programming Language :: Python :: 3.9
Classifier: Programming Language :: Python :: 3.10
Classifier: Programming Language :: Python :: 3.11
Classifier: Programming Language :: Python :: 3.12
Classifier: Programming Language :: Python :: 3.13
Classifier: Programming Language :: Python :: Implementation :: CPython
Classifier: Topic :: Software Development :: Libraries :: Python Modules
Requires-Python: >=3.6
License-File: LICENSE
Requires-Dist: attrs>=18.2.0
Requires-Dist: typing-extensions
Provides-Extra: zstd
Requires-Dist: zstd; extra == "zstd"
Provides-Extra: dev
Requires-Dist: pytest; extra == "dev"
Requires-Dist: pytest-cov; extra == "dev"
Requires-Dist: black; extra == "dev"
Requires-Dist: ruff; extra == "dev"
Requires-Dist: mypy; extra == "dev"
Requires-Dist: sphinx; extra == "dev"
Requires-Dist: sphinx-sitemap; extra == "dev"
Requires-Dist: myst-parser; extra == "dev"
Requires-Dist: furo; extra == "dev"
Provides-Extra: tests
Requires-Dist: pytest; extra == "tests"
Requires-Dist: pytest-cov; extra == "tests"
Requires-Dist: black; extra == "tests"
Requires-Dist: ruff; extra == "tests"
Requires-Dist: mypy; extra == "tests"
Provides-Extra: build
Requires-Dist: build; extra == "build"
